README.rst
setup.py
helga_bugzilla/__init__.py
helga_bugzilla/exceptions.py
helga_bugzilla/utils.py
helga_bugzilla.egg-info/PKG-INFO
helga_bugzilla.egg-info/SOURCES.txt
helga_bugzilla.egg-info/dependency_links.txt
helga_bugzilla.egg-info/entry_points.txt
helga_bugzilla.egg-info/requires.txt
helga_bugzilla.egg-info/top_level.txt
helga_bugzilla/actions/__init__.py
helga_bugzilla/actions/describe.py
helga_bugzilla/actions/search_external.py