Metadata-Version: 1.1
Name: helga-bugzilla
Version: 1.3.2
Summary: bugzilla plugin for helga
Home-page: https://github.com/ktdreyer/helga-bugzilla
Author: ken dreyer
Author-email: ktdreyer@ktdreyer.com
License: MIT
Keywords: irc bot bugzilla
Platform: UNKNOWN
Classifier: Development Status :: 4 - Beta
Classifier: License :: OSI Approved :: MIT License
Classifier: Operating System :: OS Independent
Classifier: Programming Language :: Python
Classifier: Topic :: Software Development :: Bug Tracking
